whaaaaat/__init__.py
whaaaaat-0.0.0a1.dist-info/METADATA
whaaaaat-0.0.0a1.dist-info/WHEEL
whaaaaat-0.0.0a1.dist-info/RECORD
